LICENSE
README.md
setup.cfg
setup.py
v4.py
v4xyz.egg-info/PKG-INFO
v4xyz.egg-info/SOURCES.txt
v4xyz.egg-info/dependency_links.txt
v4xyz.egg-info/entry_points.txt
v4xyz.egg-info/requires.txt
v4xyz.egg-info/top_level.txt