Metadata-Version: 2.1
Name: v4xyz
Version: 0.0.6
Summary: A command line tool to chat with GPT4 and render markdown response.
Home-page: https://github.com/imhuwq/v4xyz
Author: imhuwq
Author-email: imhuwq@gmail.com
License: Apache License 2.0
Platform: UNKNOWN
Classifier: Development Status :: 4 - Beta
Classifier: Environment :: Console
Classifier: Intended Audience :: Developers
Classifier: Topic :: Communications :: Chat
Classifier: Topic :: Terminals
Classifier: Operating System :: POSIX :: Linux
Classifier: Programming Language :: Python :: 3
Classifier: Programming Language :: Python :: 3.8
Classifier: Programming Language :: Python :: 3.9
Classifier: Programming Language :: Python :: 3.10
Classifier: License :: OSI Approved :: Apache Software License
